kafka_pubsub/__init__.py
kafka_pubsub/conf.py
kafka_pubsub/config/__init__.py
kafka_pubsub/config/pubsub.py
kafka_pubsub/config/utils.py
kafka_pubsub/consumer.py
kafka_pubsub/multi_consumer_runner.py
kafka_pubsub/producer.py
kafka_pubsub/utils.py
kafka_pubsub-0.2.2.dist-info/WHEEL
kafka_pubsub-0.2.2.dist-info/METADATA
kafka_pubsub-0.2.2.dist-info/RECORD
